nonebot_plugin_test/__init__.py
nonebot_plugin_test/dist/favicon.ico
nonebot_plugin_test/dist/index.html
nonebot_plugin_test/dist/static/css/app.d0815a94.css
nonebot_plugin_test/dist/static/css/chunk-vendors.c3c2c5a6.css
nonebot_plugin_test/dist/static/img/logo.2a63bac0.png
nonebot_plugin_test/dist/static/js/app.f38d620b.js
nonebot_plugin_test/dist/static/js/chunk-vendors.b5804d3c.js
nonebot_plugin_test/drivers/fastapi.py
nonebot_plugin_test/exception.py
nonebot_plugin_test/utils.py
nonebot_plugin_test/view.py
nonebot_plugin_test-0.3.0.dist-info/LICENSE
nonebot_plugin_test-0.3.0.dist-info/WHEEL
nonebot_plugin_test-0.3.0.dist-info/METADATA
nonebot_plugin_test-0.3.0.dist-info/RECORD
