Metadata-Version: 2.1
Name: nonebot-plugin-test
Version: 0.3.0
Summary: Test frontend for nonebot v2+
Home-page: https://v2.nonebot.dev/
License: MIT
Keywords: nonebot,qq,qqbot,mirai,cqhttp
Author: yanyongyu
Author-email: yanyongyu_1@126.com
Requires-Python: >=3.7.3,<4.0.0
Classifier: License :: OSI Approved :: MIT License
Classifier: Programming Language :: Python :: 3
Classifier: Programming Language :: Python :: 3.8
Classifier: Programming Language :: Python :: 3.9
Requires-Dist: aiofiles (>=0.7.0,<0.8.0)
Requires-Dist: nonebot2 (>=2.0.0-alpha.14,<3.0.0)
Requires-Dist: python-socketio (>=4.6.1,<5.0.0)
Project-URL: Repository, https://github.com/nonebot/plugin-test
